aaaaa_future_breakpoint.pth
_future_breakpoint.cpython-39-x86_64-linux-gnu.so
future_breakpoint-2.0.0.dist-info/top_level.txt
future_breakpoint-2.0.0.dist-info/METADATA
future_breakpoint-2.0.0.dist-info/RECORD
future_breakpoint-2.0.0.dist-info/LICENSE
future_breakpoint-2.0.0.dist-info/WHEEL
